[
  {
    "id": "caspers", "name": "Ronald W. Caspers Wilderness Park", "agency": "OC Parks",
    "reservationType": "manual", "reservationUrl": "https://www.ocparks.com/parks/caspers/camping",
    "distanceMiles": 22, "driveMinutes": 35, "elevation": 200, "lat": 33.5908, "lng": -117.5095,
    "difficulty": "Easy", "kidFriendly": true, "tentOk": true, "rvOk": true,
    "hasWater": false, "hasShowers": false, "hasElectric": true, "pricePerNight": 20,
    "eBirdHotspot": "L286407", "eBirdUrl": "https://ebird.org/hotspot/L286407",
    "highlights": "8,000-acre canyon park just off Ortega Hwy. Family trails like Mesa Loop (1 mi) and West Ridge (2.3 mi). Nature center with observation deck. No dogs permitted.",
    "trails": [
      { "name": "Mesa Loop Trail", "distance": "1 mi", "difficulty": "Easy" },
      { "name": "West Ridge Trail", "distance": "2.3 mi", "difficulty": "Easy" },
      { "name": "Juaneno Trail", "distance": "2.7 mi", "difficulty": "Easy–Moderate" }
    ],
    "birds": [
      { "name": "California Quail", "sciName": "Callipepla californica", "photoKey": "california-quail" },
      { "name": "Cooper's Hawk", "sciName": "Accipiter cooperii", "photoKey": "coopers-hawk" },
      { "name": "Acorn Woodpecker", "sciName": "Melanerpes formicivorus", "photoKey": "acorn-woodpecker" },
      { "name": "Wrentit", "sciName": "Chamaea fasciata", "photoKey": "wrentit" },
      { "name": "Anna's Hummingbird", "sciName": "Calypte anna", "photoKey": "annas-hummingbird" }
    ]
  },
  {
    "id": "oneill", "name": "O'Neill Regional Park", "agency": "OC Parks",
    "reservationType": "manual", "reservationUrl": "https://www.ocparks.com/parks/oneill/camping",
    "distanceMiles": 18, "driveMinutes": 30, "elevation": 900, "lat": 33.6517, "lng": -117.6003,
    "difficulty": "Easy", "kidFriendly": true, "tentOk": true, "rvOk": true,
    "hasWater": true, "hasShowers": true, "hasElectric": false, "pricePerNight": 20,
    "eBirdHotspot": "L374421", "eBirdUrl": "https://ebird.org/hotspot/L374421",
    "highlights": "Closest campground to Irvine at ~18 miles. Canyon setting along Trabuco Creek with riparian oak woodland. Great for birding the creek corridor.",
    "trails": [
      { "name": "Trabuco Creek Trail", "distance": "2 mi", "difficulty": "Easy" },
      { "name": "Live Oak Trail", "distance": "1.5 mi", "difficulty": "Easy" },
      { "name": "Bell View Trail", "distance": "3.5 mi", "difficulty": "Easy–Moderate" }
    ],
    "birds": [
      { "name": "Yellow Warbler", "sciName": "Setophaga petechia", "photoKey": "yellow-warbler" },
      { "name": "Black Phoebe", "sciName": "Sayornis nigricans", "photoKey": "black-phoebe" },
      { "name": "Hooded Oriole", "sciName": "Icterus cucullatus", "photoKey": "hooded-oriole" },
      { "name": "California Towhee", "sciName": "Melozone crissalis", "photoKey": "california-towhee" },
      { "name": "Bewick's Wren", "sciName": "Thryomanes bewickii", "photoKey": "bewickss-wren" }
    ]
  },
  {
    "id": "falcon", "name": "Falcon Group Campground", "agency": "USDA Forest Service",
    "reservationType": "recreation.gov", "facilityId": "231947",
    "reservationUrl": "https://www.recreation.gov/camping/campgrounds/231947",
    "distanceMiles": 38, "driveMinutes": 55, "elevation": 3300, "lat": 33.6011, "lng": -117.4489,
    "difficulty": "Easy", "kidFriendly": true, "tentOk": true, "rvOk": false,
    "hasWater": true, "hasShowers": false, "hasElectric": false, "pricePerNight": 60,
    "eBirdHotspot": "L5928152", "eBirdUrl": "https://ebird.org/hotspot/L5928152",
    "highlights": "Group sites at 3,300 ft in Santa Ana Mountains. Easy Falcon Trail (1.4 mi) starts at camp. Adjacent to Blue Jay Campground.",
    "trails": [
      { "name": "Falcon Trail", "distance": "1.4 mi", "difficulty": "Easy" },
      { "name": "Trabuco Canyon Trail", "distance": "6.8 mi", "difficulty": "Moderate" }
    ],
    "birds": [
      { "name": "California Gnatcatcher", "sciName": "Polioptila californica", "photoKey": "california-gnatcatcher" },
      { "name": "Cactus Wren", "sciName": "Campylorhynchus brunneicapillus", "photoKey": "cactus-wren" },
      { "name": "Greater Roadrunner", "sciName": "Geococcyx californianus", "photoKey": "greater-roadrunner" },
      { "name": "White-tailed Kite", "sciName": "Elanus leucurus", "photoKey": "white-tailed-kite" },
      { "name": "Nuttall's Woodpecker", "sciName": "Dryobates nuttallii", "photoKey": "nuttalls-woodpecker" }
    ]
  },
  {
    "id": "dripping-springs", "name": "Dripping Springs Campground", "agency": "USDA Forest Service",
    "reservationType": "recreation.gov", "facilityId": "234719",
    "reservationUrl": "https://www.recreation.gov/camping/campgrounds/234719",
    "distanceMiles": 50, "driveMinutes": 70, "elevation": 1500, "lat": 33.4608, "lng": -116.9702,
    "difficulty": "Easy–Moderate", "kidFriendly": true, "tentOk": true, "rvOk": true,
    "hasWater": true, "hasShowers": false, "hasElectric": false, "pricePerNight": 25,
    "eBirdHotspot": "L2455088", "eBirdUrl": "https://ebird.org/hotspot/L2455088",
    "highlights": "Adjacent to Agua Tibia Wilderness near Temecula. Riparian habitat. 30+ miles of connected trails.",
    "trails": [
      { "name": "Dripping Springs Trail", "distance": "4 mi", "difficulty": "Easy–Moderate" },
      { "name": "Wildhorse Trail", "distance": "8 mi", "difficulty": "Moderate" }
    ],
    "birds": [
      { "name": "Least Bell's Vireo", "sciName": "Vireo bellii pusillus", "photoKey": "least-bells-vireo" },
      { "name": "Lawrence's Goldfinch", "sciName": "Spinus lawrencei", "photoKey": "lawrences-goldfinch" },
      { "name": "Rufous-crowned Sparrow", "sciName": "Aimophila ruficeps", "photoKey": "rufous-crowned-sparrow" },
      { "name": "Costa's Hummingbird", "sciName": "Calypte costae", "photoKey": "costas-hummingbird" },
      { "name": "California Thrasher", "sciName": "Toxostoma redivivum", "photoKey": "california-thrasher" }
    ]
  },
  {
    "id": "burnt-rancheria", "name": "Burnt Rancheria Campground", "agency": "USDA Forest Service",
    "reservationType": "recreation.gov", "facilityId": "232278",
    "reservationUrl": "https://www.recreation.gov/camping/campgrounds/232278",
    "distanceMiles": 58, "driveMinutes": 80, "elevation": 6000, "lat": 32.8612, "lng": -116.4204,
    "difficulty": "Easy", "kidFriendly": true, "tentOk": true, "rvOk": true,
    "hasWater": true, "hasShowers": true, "hasElectric": false, "pricePerNight": 35,
    "eBirdHotspot": "L800393", "eBirdUrl": "https://ebird.org/hotspot/L800393",
    "highlights": "6,000 ft elevation in Laguna Mountains. PCT access. Ranger-led programs and star parties in summer. Open mid-April through October.",
    "trails": [
      { "name": "Desert View Trail", "distance": "1 mi", "difficulty": "Easy" },
      { "name": "Pacific Crest Trail (segment)", "distance": "3 mi", "difficulty": "Easy–Moderate" },
      { "name": "Big Laguna Trail", "distance": "5 mi", "difficulty": "Easy–Moderate" }
    ],
    "birds": [
      { "name": "Mountain Chickadee", "sciName": "Poecile gambeli", "photoKey": "mountain-chickadee" },
      { "name": "Steller's Jay", "sciName": "Cyanocitta stelleri", "photoKey": "stellers-jay" },
      { "name": "Hairy Woodpecker", "sciName": "Dryobates villosus", "photoKey": "hairy-woodpecker" },
      { "name": "Western Bluebird", "sciName": "Sialia mexicana", "photoKey": "western-bluebird" },
      { "name": "Red-breasted Nuthatch", "sciName": "Sitta canadensis", "photoKey": "red-breasted-nuthatch" }
    ]
  },
  {
    "id": "laguna", "name": "Laguna Campground", "agency": "USDA Forest Service",
    "reservationType": "recreation.gov", "facilityId": "232279",
    "reservationUrl": "https://www.recreation.gov/camping/campgrounds/232279",
    "distanceMiles": 58, "driveMinutes": 80, "elevation": 6000, "lat": 32.8700, "lng": -116.4350,
    "difficulty": "Easy", "kidFriendly": true, "tentOk": true, "rvOk": true,
    "hasWater": true, "hasShowers": true, "hasElectric": false, "pricePerNight": 35,
    "eBirdHotspot": "L1113334", "eBirdUrl": "https://ebird.org/hotspot/L1113334",
    "highlights": "Large mountain campground at 6,000 ft with 5 loops. Little Laguna Lake nearby. Big Laguna Trail for wildflowers in spring.",
    "trails": [
      { "name": "Laguna Meadow Trail", "distance": "2 mi", "difficulty": "Easy" },
      { "name": "Big Laguna Trail", "distance": "5 mi", "difficulty": "Easy" },
      { "name": "Pacific Crest Trail (segment)", "distance": "4 mi", "difficulty": "Easy–Moderate" }
    ],
    "birds": [
      { "name": "Mountain Bluebird", "sciName": "Sialia currucoides", "photoKey": "mountain-bluebird" },
      { "name": "Steller's Jay", "sciName": "Cyanocitta stelleri", "photoKey": "stellers-jay" },
      { "name": "Lawrence's Goldfinch", "sciName": "Spinus lawrencei", "photoKey": "lawrences-goldfinch" },
      { "name": "White-headed Woodpecker", "sciName": "Dryobates albolarvatus", "photoKey": "white-headed-woodpecker" },
      { "name": "Pygmy Nuthatch", "sciName": "Sitta pygmaea", "photoKey": "pygmy-nuthatch" }
    ]
  }
]
